pymmcore_mda_writers/__init__.py
pymmcore_mda_writers/_version.py
pymmcore_mda_writers/_writers.py
tests/__init__.py
tests/test_pymmcore_mda_writers.py
tests/test_utils.py
pymmcore_MDA_writers-0.5.0.dist-info/LICENSE
pymmcore_MDA_writers-0.5.0.dist-info/METADATA
pymmcore_MDA_writers-0.5.0.dist-info/WHEEL
pymmcore_MDA_writers-0.5.0.dist-info/top_level.txt
pymmcore_MDA_writers-0.5.0.dist-info/RECORD
