Metadata-Version: 2.1
Name: pymmcore-MDA-writers
Version: 0.5.0
Summary: MDA writers for pymmcore-plus
Home-page: https://github.com/ianhi/pymmcore-MDA-writers
Author: Ian Hunt-Isaak
Author-email: ianhuntisaak@gmail.com
License: BSD-3-Clause
Project-URL: Source Code, https://github.com/ianhi/pymmcore-MDA-writers
Classifier: Development Status :: 2 - Pre-Alpha
Classifier: License :: OSI Approved :: BSD License
Classifier: Natural Language :: English
Classifier: Programming Language :: Python :: 3
Classifier: Programming Language :: Python :: 3 :: Only
Requires-Python: >=3.7
License-File: LICENSE
Requires-Dist: numpy
Requires-Dist: pymmcore-plus
Provides-Extra: dev
Requires-Dist: black ; extra == 'dev'
Requires-Dist: flake8 ; extra == 'dev'
Requires-Dist: flake8-docstrings ; extra == 'dev'
Requires-Dist: ipython ; extra == 'dev'
Requires-Dist: isort ; extra == 'dev'
Requires-Dist: jedi (<0.18.0) ; extra == 'dev'
Requires-Dist: mypy ; extra == 'dev'
Requires-Dist: pre-commit ; extra == 'dev'
Requires-Dist: pydocstyle ; extra == 'dev'
Requires-Dist: pytest ; extra == 'dev'
Provides-Extra: testing
Requires-Dist: pymmcore-plus ; extra == 'testing'
Requires-Dist: pytest ; extra == 'testing'
Requires-Dist: pytest-cov ; extra == 'testing'
Requires-Dist: pytest-qt ; extra == 'testing'
Requires-Dist: qtpy ; extra == 'testing'
Requires-Dist: tifffile ; extra == 'testing'
Requires-Dist: tox ; extra == 'testing'
Requires-Dist: tox-conda ; extra == 'testing'
Requires-Dist: zarr ; extra == 'testing'
